mseep_mcp_taiga_bridge-0.1.1.dist-info/licenses/LICENSE
src/__init__.py
src/server.py
src/taiga_client.py
mseep_mcp_taiga_bridge-0.1.1.dist-info/METADATA
mseep_mcp_taiga_bridge-0.1.1.dist-info/WHEEL
mseep_mcp_taiga_bridge-0.1.1.dist-info/top_level.txt
mseep_mcp_taiga_bridge-0.1.1.dist-info/RECORD
